pyasq/__init__.py
pyasq/conversion.py
pyasq/endpoint.py
pyasq/utils.py
pyasq/validation.py
pyasq-0.0.2.dist-info/DESCRIPTION.rst
pyasq-0.0.2.dist-info/METADATA
pyasq-0.0.2.dist-info/RECORD
pyasq-0.0.2.dist-info/WHEEL
pyasq-0.0.2.dist-info/metadata.json
pyasq-0.0.2.dist-info/top_level.txt
