Metadata-Version: 2.0
Name: pyasq
Version: 0.0.2
Summary: A pure Python API API.
Home-page: http://github.com/textbook/pyasq/
Author: Jonathan Sharpe
Author-email: mail@jonrshar.pe
License: License :: OSI Approved :: ISC License (ISCL)
Platform: any
Classifier: Development Status :: 3 - Alpha
Classifier: Intended Audience :: Developers
Classifier: Natural Language :: English
Classifier: Operating System :: OS Independent
Classifier: Programming Language :: Python :: 3.6
Classifier: Programming Language :: Python :: 3 :: Only
Requires-Dist: requests
